{"cameraMode":{"drawMode":0,"name":"Shaded","section":"Shading Mode"},"sceneLighting":false,"audioPlay":false,"sceneViewState":{"m_AlwaysRefresh":false,"showFog":true,"showSkybox":false,"showFlares":true,"showImageEffects":true,"showParticleSystems":true,"showVisualEffectGraphs":true,"m_FxEnabled":true},"in2DMode":false,"pivot":{"x":-13.672120094299317,"y":16.523792266845704,"z":-7.422304630279541},"rotation":{"x":-0.2628537714481354,"y":-0.6738928556442261,"z":0.2808034121990204,"w":-0.6308157444000244},"size":5.407395362854004,"orthographic":false}